MANIFEST.in
README.md
setup.py
wxutil/__init__.py
wxutil/db_v3.py
wxutil/db_v4.py
wxutil/logger.py
wxutil/utils.py
wxutil.egg-info/PKG-INFO
wxutil.egg-info/SOURCES.txt
wxutil.egg-info/dependency_links.txt
wxutil.egg-info/requires.txt
wxutil.egg-info/top_level.txt
wxutil/tools/DbkeyHookCMD.exe
wxutil/tools/wechat-dump-rs.exe