Metadata-Version: 2.2
Name: wxutil
Version: 0.0.8
Summary: wechat utils.
Home-page: https://github.com/miloira/wxutil
Author: Msky
Author-email: 690126048@qq.com
License: MIT
Classifier: License :: OSI Approved :: MIT License
Classifier: Programming Language :: Python
Classifier: Programming Language :: Python :: 3
Classifier: Programming Language :: Python :: 3.8
Classifier: Programming Language :: Python :: Implementation :: CPython
Classifier: Programming Language :: Python :: Implementation :: PyPy
Requires-Python: >=3.8.0
Requires-Dist: blackboxprotobuf
Requires-Dist: loguru
Requires-Dist: lz4
Requires-Dist: pyee
Requires-Dist: pycryptodome
Requires-Dist: pymem
Requires-Dist: sqlcipher3-wheels
Requires-Dist: xmltodict
Requires-Dist: zstandard
Dynamic: author
Dynamic: author-email
Dynamic: classifier
Dynamic: description
Dynamic: description-content-type
Dynamic: home-page
Dynamic: license
Dynamic: requires-dist
Dynamic: requires-python
Dynamic: summary
